ioc/__init__.py
ioc/component.py
ioc/event.py
ioc/exceptions.py
ioc/helper.py
ioc/loader.py
ioc/locator.py
ioc/misc.py
ioc/proxy.py
ioc/extra/__init__.py
ioc/extra/command/__init__.py
ioc/extra/command/command.py
ioc/extra/command/di.py
ioc/extra/command/resources/config/command.yml
ioc/extra/event/__init__.py
ioc/extra/event/di.py
ioc/extra/flask/__init__.py
ioc/extra/flask/command.py
ioc/extra/flask/di.py
ioc/extra/flask/resources/config/flask.yml
ioc/extra/jinja2/__init__.py
ioc/extra/jinja2/di.py
ioc/extra/jinja2/helper.py
ioc/extra/jinja2/resources/config/jinja.yml
ioc/extra/locator/__init__.py
ioc/extra/locator/di.py
ioc/extra/mailer/__init__.py
ioc/extra/mailer/di.py
ioc/extra/redis/__init__.py
ioc/extra/redis/di.py
ioc/extra/redis/resources/config/redis.yml
ioc-0.1.18.dist-info/licenses/LICENSE
ioc-0.1.18.dist-info/METADATA
ioc-0.1.18.dist-info/WHEEL
ioc-0.1.18.dist-info/top_level.txt
ioc-0.1.18.dist-info/RECORD
