Metadata-Version: 2.4
Name: ioc
Version: 0.1.18
Summary: A small dependency injection container based on Symfony2 Dependency Component
Author-email: Thomas Rabaix <thomas.rabaix@gmail.com>
Maintainer-email: Thomas Rabaix <thomas.rabaix@gmail.com>
License-Expression: Apache-2.0
Project-URL: Homepage, https://github.com/rande/python-simple-ioc
Project-URL: Repository, https://github.com/rande/python-simple-ioc
Project-URL: Issues, https://github.com/rande/python-simple-ioc/issues
Keywords: dependency injection,ioc,container,symfony
Classifier: Development Status :: 4 - Beta
Classifier: Intended Audience :: Developers
Classifier: Operating System :: OS Independent
Classifier: Programming Language :: Python :: 3
Classifier: Programming Language :: Python :: 3.9
Classifier: Programming Language :: Python :: 3.10
Classifier: Programming Language :: Python :: 3.11
Classifier: Programming Language :: Python :: 3.12
Classifier: Programming Language :: Python :: 3.13
Classifier: Topic :: Software Development :: Libraries :: Python Modules
Classifier: Topic :: Utilities
Requires-Python: >=3.9
License-File: LICENSE
Requires-Dist: pyyaml
Provides-Extra: dev
Requires-Dist: flake8>=6.0.0; extra == "dev"
Requires-Dist: mypy>=1.0.0; extra == "dev"
Requires-Dist: build>=0.10.0; extra == "dev"
Requires-Dist: twine>=4.0.0; extra == "dev"
Provides-Extra: test
Requires-Dist: pytest>=6.0; extra == "test"
Provides-Extra: flask
Requires-Dist: flask; extra == "flask"
Requires-Dist: werkzeug; extra == "flask"
Provides-Extra: jinja2
Requires-Dist: jinja2; extra == "jinja2"
Provides-Extra: redis
Requires-Dist: redis; extra == "redis"
Dynamic: license-file
